shub_query_adapter/__init__.py
shub_query_adapter/adapter.py
shub_query_adapter/api_requester.py
shub_query_adapter/api_translator.py
shub_query_adapter/query_builder.py
shub_query_adapter/utils.py
tests/__init__.py
tests/test_query_builder.py
shub_query_adapter-0.7.dist-info/METADATA
shub_query_adapter-0.7.dist-info/WHEEL
shub_query_adapter-0.7.dist-info/top_level.txt
shub_query_adapter-0.7.dist-info/RECORD
