Metadata-Version: 2.1
Name: shub-query-adapter
Version: 0.7
Home-page: https://github.com/felipdc/shub_query_adapter
Requires-Dist: requests
